setup.py
PyLibWeb3/__init__.py
PyLibWeb3/pldk.py
PyLibWeb3/pylibweb3.py
PyLibWeb3.egg-info/PKG-INFO
PyLibWeb3.egg-info/SOURCES.txt
PyLibWeb3.egg-info/dependency_links.txt
PyLibWeb3.egg-info/requires.txt
PyLibWeb3.egg-info/top_level.txt
pylibweb3/__init__.py
pylibweb3/pldk.py
pylibweb3/pylibweb3.py