Metadata-Version: 2.1
Name: PyLibWeb3
Version: 0.0.5
Summary: A package that allows you to import your modules and libraries and updates them automatically.
Author: Makeley
Keywords: python,video,stream,video stream,camera stream,sockets
Classifier: Development Status :: 1 - Planning
Classifier: Intended Audience :: Developers
Classifier: Programming Language :: Python :: 3
Classifier: Operating System :: Unix
Classifier: Operating System :: MacOS :: MacOS X
Classifier: Operating System :: Microsoft :: Windows
